omnigraffle_stencil/__init__.py
omnigraffle_stencil/__main__.py
omnigraffle_stencil/converter.py
omnigraffle_stencil/templates/data.plist
omnigraffle_stencil/templates/image.plist
omnigraffle_stencil/templates/sheet.plist
omnigraffle_stencil-1.1.0.dist-info/entry_points.txt
omnigraffle_stencil-1.1.0.dist-info/LICENSE
omnigraffle_stencil-1.1.0.dist-info/WHEEL
omnigraffle_stencil-1.1.0.dist-info/METADATA
omnigraffle_stencil-1.1.0.dist-info/RECORD
