Metadata-Version: 2.1
Name: omnigraffle-stencil
Version: 1.1.0
Summary: Tool to create OmniGraffle stencils from SVG icons
Home-page: https://github.com/m-radzikowski/omnigraffle-stencil
License: MIT
Keywords: omnigraffle,stencil,svg
Author: Maciej Radzikowski
Author-email: maciej@radzikowski.com.pl
Requires-Python: >=3.8,<4.0
Classifier: Development Status :: 5 - Production/Stable
Classifier: Environment :: Console
Classifier: License :: OSI Approved :: MIT License
Classifier: Operating System :: MacOS :: MacOS X
Classifier: Programming Language :: Python :: 3
Classifier: Programming Language :: Python :: 3.8
Classifier: Programming Language :: Python :: 3.9
Classifier: Topic :: Multimedia :: Graphics :: Graphics Conversion
Requires-Dist: PyPDF2 (==1.26.0)
Requires-Dist: cairosvg (==2.4.2)
Project-URL: Repository, https://github.com/m-radzikowski/omnigraffle-stencil
